metsuke/__init__.py
metsuke/__main__.py
metsuke/cli.py
metsuke/core.py
metsuke/exceptions.py
metsuke/models.py
metsuke/tui/__init__.py
metsuke/tui/app.py
metsuke/tui/handlers.py
metsuke/tui/screens.py
metsuke/tui/widgets.py
metsuke-0.1.4.dist-info/licenses/LICENSE
metsuke-0.1.4.dist-info/METADATA
metsuke-0.1.4.dist-info/WHEEL
metsuke-0.1.4.dist-info/entry_points.txt
metsuke-0.1.4.dist-info/top_level.txt
metsuke-0.1.4.dist-info/RECORD
