Metadata-Version: 2.4
Name: metsuke
Version: 0.1.4
Summary: AI-Assisted Development Task Manager using YAML plans.
License-Expression: Apache-2.0
Project-URL: Homepage, https://github.com/cidxb/metsuke
Project-URL: Bug Tracker, https://github.com/cidxb/metsuke/issues
Classifier: Programming Language :: Python :: 3
Classifier: Operating System :: OS Independent
Classifier: Development Status :: 3 - Alpha
Classifier: Intended Audience :: Developers
Classifier: Topic :: Software Development :: Build Tools
Classifier: Topic :: Utilities
Requires-Python: >=3.10
License-File: LICENSE
Requires-Dist: PyYAML>=6.0
Requires-Dist: pydantic>=2.0
Requires-Dist: click>=8.0
Requires-Dist: toml>=0.10.0
Requires-Dist: textual>=0.50.0
Requires-Dist: watchdog>=2.0.0
Requires-Dist: pyperclip>=1.8.0
Requires-Dist: ruamel.yaml>=0.17.0
Provides-Extra: dev
Requires-Dist: pytest>=7.0; extra == "dev"
Requires-Dist: pytest-cov; extra == "dev"
Requires-Dist: flake8; extra == "dev"
Requires-Dist: mypy; extra == "dev"
Requires-Dist: black; extra == "dev"
Requires-Dist: isort; extra == "dev"
Dynamic: license-file
